YAX-1.2.0.dist-info/DESCRIPTION.rst
YAX-1.2.0.dist-info/METADATA
YAX-1.2.0.dist-info/RECORD
YAX-1.2.0.dist-info/WHEEL
YAX-1.2.0.dist-info/metadata.json
YAX-1.2.0.dist-info/top_level.txt
yax/YAXReader.py
yax/__init__.py
yax/condition.py
