Metadata-Version: 2.0
Name: YAX
Version: 1.2.0
Summary: Yet Another XML parser with the power of event-based memory-safe mechanism.
Home-page: https://github.com/morta-code/YAX
Author: Móréh Tamás, MTA-PPKE-NLPG
Author-email: morta@digitus.itk.ppke.hu
License: LGPLv3
Keywords: xml lxml parser event-based record-oriented
Platform: UNKNOWN
Classifier: Development Status :: 5 - Production/Stable
Classifier: Environment :: Console
Classifier: Intended Audience :: Information Technology
Classifier: Intended Audience :: Science/Research
Classifier: Intended Audience :: Developers
Classifier: License :: OSI Approved :: GNU Lesser General Public License v3 (LGPLv3)
Classifier: Programming Language :: Python :: 3
Classifier: Topic :: Software Development :: Libraries :: Python Modules
Classifier: Topic :: Text Processing :: Markup :: XML
